<?xml version="1.0" encoding="UTF-8"?>
<persistence xmlns="http://java.sun.com/xml/ns/persistence" version="2.0">

    <persistence-unit name="persistenceUnit">
        <class>org.molw.data.BirdobsEntity</class>
        <class>org.molw.data.MarineobsEntity</class>
        <properties>
            <property name="hibernate.connection.url" value="jdbc:postgresql://localhost:5432/molw"/>
            <property name="hibernate.connection.driver_class" value="org.postgresql.Driver"/>
            <property name="hibernate.dialect" value="org.hibernate.spatial.dialect.postgis.PostgisDialect"/>
            <property name="hibernate.c3p0.min_size" value="5" />
            <property name="hibernate.c3p0.max_size" value="30" />
            <property name="hibernate.c3p0.max_statements" value="50" />
            <property name="hibernate.connection.username" value="spousty"/>
            <property name="hibernate.connection.password" value="notsafe"/>
        </properties>
    </persistence-unit>
</persistence>
